mongodiskdb/__init__.py
mongodiskdb/__main__.py
mongodiskdb/cli.py
mongodiskdb/collection.py
mongodiskdb/db.py
mongodiskdb/exceptions.py
mongodiskdb/viewer.py
mongodiskdb/templates/base.html
mongodiskdb/templates/documents.html
mongodiskdb/templates/error.html
mongodiskdb/templates/index.html
mongodiskdb/templates/query.html
mongodiskdb-1.0.2.dist-info/licenses/LICENSE
mongodiskdb-1.0.2.dist-info/METADATA
mongodiskdb-1.0.2.dist-info/WHEEL
mongodiskdb-1.0.2.dist-info/entry_points.txt
mongodiskdb-1.0.2.dist-info/top_level.txt
mongodiskdb-1.0.2.dist-info/RECORD
