Metadata-Version: 2.4
Name: mongodiskdb
Version: 1.0.2
Summary: A MongoDB-style disk-based persistent database developed using diskcache, additional features include viewing and querying documents
Home-page: https://github.com/anandan-bs/mongodiskdb
Author: Anandan B S
Author-email: anandanklnce@gmail.com
Classifier: Development Status :: 5 - Production/Stable
Classifier: Intended Audience :: Developers
Classifier: License :: OSI Approved :: MIT License
Classifier: Operating System :: OS Independent
Classifier: Programming Language :: Python :: 3
Classifier: Programming Language :: Python :: 3.7
Classifier: Programming Language :: Python :: 3.8
Classifier: Programming Language :: Python :: 3.9
Classifier: Programming Language :: Python :: 3.10
Requires-Python: >=3.7
License-File: LICENSE
Requires-Dist: diskcache>=5.0.0
Requires-Dist: flask>=2.0.0
Dynamic: author
Dynamic: author-email
Dynamic: classifier
Dynamic: description
Dynamic: description-content-type
Dynamic: home-page
Dynamic: license-file
Dynamic: requires-dist
Dynamic: requires-python
Dynamic: summary
